[
  {
    "ok": true,
    "stmt": "CREATE TABLE IF NOT EXISTS dim_scoreboard ("
  },
  {
    "ok": true,
    "stmt": "CREATE TABLE IF NOT EXISTS dim_team ("
  },
  {
    "ok": true,
    "stmt": "CREATE TABLE IF NOT EXISTS dim_discipline ("
  },
  {
    "ok": true,
    "stmt": "CREATE TABLE IF NOT EXISTS dim_athlete ("
  },
  {
    "ok": true,
    "stmt": "CREATE TABLE IF NOT EXISTS map_roster ("
  },
  {
    "ok": true,
    "stmt": "CREATE TABLE IF NOT EXISTS dim_stage ("
  },
  {
    "ok": true,
    "stmt": "CREATE TABLE IF NOT EXISTS dim_series ("
  },
  {
    "ok": true,
    "stmt": "CREATE TABLE IF NOT EXISTS fact_stage_series_result ("
  },
  {
    "ok": true,
    "stmt": "CREATE TABLE IF NOT EXISTS fact_penalty ("
  },
  {
    "ok": true,
    "stmt": "CREATE UNIQUE INDEX IF NOT EXISTS ux_fact_penalty_unique ON fact_penalty ("
  },
  {
    "ok": true,
    "stmt": "CREATE TABLE IF NOT EXISTS fact_stage_total ("
  },
  {
    "ok": true,
    "stmt": "CREATE TABLE IF NOT EXISTS silver_property ("
  },
  {
    "ok": true,
    "stmt": "CREATE INDEX IF NOT EXISTS ix_fact_result_discipline_stage ON fact_stage_series_result (discipline_id, stage_num, value)"
  },
  {
    "ok": true,
    "stmt": "CREATE INDEX IF NOT EXISTS ix_map_roster_scoreboard_team ON map_roster (scoreboard_id, team_id)"
  }
]